<annotation>
	<folder>imgs</folder>
	<filename>109.JPG</filename>
	<path>C:\Users\SanReiZan\Documents\darkflow\darkflow-master\RebarModel\imgs\109.JPG</path>
	<source>
		<database>Unknown</database>
	</source>
	<size>
		<width>4032</width>
		<height>3024</height>
		<depth>3</depth>
	</size>
	<segmented>0</segmented>
	<object>
		<name>rebar_tied</name>
		<pose>Unspecified</pose>
		<truncated>0</truncated>
		<difficult>0</difficult>
		<bndbox>
			<xmin>1671</xmin>
			<ymin>359</ymin>
			<xmax>2639</xmax>
			<ymax>1474</ymax>
		</bndbox>
	</object>
	<object>
		<name>rebar_untied</name>
		<pose>Unspecified</pose>
		<truncated>0</truncated>
		<difficult>0</difficult>
		<bndbox>
			<xmin>1658</xmin>
			<ymin>2406</ymin>
			<xmax>2527</xmax>
			<ymax>2999</ymax>
		</bndbox>
	</object>
</annotation>
